rabbitmq_spider/__init__.py
rabbitmq_spider/connection.py
rabbitmq_spider/middlewares.py
rabbitmq_spider/spiders.py
rabbitmq_spider-0.0.2.dist-info/METADATA
rabbitmq_spider-0.0.2.dist-info/WHEEL
rabbitmq_spider-0.0.2.dist-info/licenses/LICENSE
rabbitmq_spider-0.0.2.dist-info/RECORD
