Metadata-Version: 2.1
Name: rabbitmq-spider
Version: 0.0.2
Summary: rabbitmq-spider is an open-source tool that helps with web scraping by using RabbitMQ and Scrapy to distribute and scale scraping tasks across multiple instances.
Project-URL: Homepage, https://github.com/nobbbbby/rabbitmq-spider
Project-URL: Bug Tracker, https://github.com/nobbbbby/rabbitmq-spider/issues
Author-email: Nobby Tang <cnadytzar@gmail.com>
License-File: LICENSE
Classifier: License :: OSI Approved :: MIT License
Classifier: Operating System :: OS Independent
Classifier: Programming Language :: Python :: 3
Requires-Python: >=3.7
Requires-Dist: pika
Requires-Dist: scrapy>2.0
